<?xml version="1.0" encoding="utf-8"?>
<network version="1.0">
  <networkStructure>
    <nodes>
      <node id="Gdansk">
        <coordinates>
          <x>18.6</x>
          <y>54.2</y>
        </coordinates>
      </node>
      <node id="Bydgoszcz">
        <coordinates>
          <x>17.9</x>
          <y>53.1</y>
        </coordinates>
      </node>
      <node id="Kolobrzeg">
        <coordinates>
          <x>16.1</x>
          <y>54.2</y>
        </coordinates>
      </node>
      <node id="Katowice">
        <coordinates>
          <x>18.8</x>
          <y>50.3</y>
        </coordinates>
      </node>
      <node id="Krakow">
        <coordinates>
          <x>19.8</x>
          <y>50.0</y>
        </coordinates>
      </node>
      <node id="Bialystok">
        <coordinates>
          <x>23.1</x>
          <y>53.1</y>
        </coordinates>
      </node>
      <node id="Lodz">
        <coordinates>
          <x>19.4</x>
          <y>51.7</y>
        </coordinates>
      </node>
      <node id="Poznan">
        <coordinates>
          <x>16.8</x>
          <y>52.4</y>
        </coordinates>
      </node>
      <node id="Rzeszow">
        <coordinates>
          <x>21.9</x>
          <y>50.0</y>
        </coordinates>
      </node>
      <node id="Szczecin">
        <coordinates>
          <x>14.5</x>
          <y>53.4</y>
        </coordinates>
      </node>
      <node id="Warsaw">
        <coordinates>
          <x>21.0</x>
          <y>52.2</y>
        </coordinates>
      </node>
      <node id="Wroclaw">
        <coordinates>
          <x>16.9</x>
          <y>51.1</y>
        </coordinates>
      </node>
    </nodes>
    <links>
      <link>
        <source>Gdansk</source>
        <target>Warsaw</target>
        <distance>359.682</distance>
      </link>
      <link>
        <source>Gdansk</source>
        <target>Kolobrzeg</target>
        <distance>235.779</distance>
      </link>
      <link>
        <source>Bydgoszcz</source>
        <target>Kolobrzeg</target>
        <distance>207.321</distance>
      </link>
      <link>
        <source>Bydgoszcz</source>
        <target>Poznan</target>
        <distance>183.881</distance>
      </link>
      <link>
        <source>Bydgoszcz</source>
        <target>Warsaw</target>
        <distance>312.092</distance>
      </link>
      <link>
        <source>Kolobrzeg</source>
        <target>Szczecin</target>
        <distance>170.483</distance>
      </link>
      <link>
        <source>Katowice</source>
        <target>Krakow</target>
        <distance>97.174</distance>
      </link>
      <link>
        <source>Katowice</source>
        <target>Lodz</target>
        <distance>214.077</distance>
      </link>
      <link>
        <source>Katowice</source>
        <target>Wroclaw</target>
        <distance>160.6764818757346</distance>
      </link>
      <link>
        <source>Krakow</source>
        <target>Rzeszow</target>
        <distance>150.09198393119775</distance>
      </link>
      <link>
        <source>Krakow</source>
        <target>Warsaw</target>
        <distance>258.5716578236342</distance>
      </link>
      <link>
        <source>Bialystok</source>
        <target>Rzeszow</target>
        <distance>438.901</distance>
      </link>
      <link>
        <source>Bialystok</source>
        <target>Warsaw</target>
        <distance>203.968</distance>
      </link>
      <link>
        <source>Lodz</source>
        <target>Warsaw</target>
        <distance>140.941</distance>
      </link>
      <link>
        <source>Lodz</source>
        <target>Wroclaw</target>
        <distance>185.80862973600003</distance>
      </link>
      <link>
        <source>Poznan</source>
        <target>Szczecin</target>
        <distance>266.866</distance>
      </link>
      <link>
        <source>Poznan</source>
        <target>Wroclaw</target>
        <distance>144.7171881290013</distance>
      </link>
      <link>
        <source>Gdansk</source>
        <target>Bialystok</target>
        <distance>537.391</distance>
      </link>
    </links>
  </networkStructure>
</network>
